Zeppi_ConvertX/__init__.py
Zeppi_ConvertX/__main__.py
Zeppi_ConvertX-0.1.8.dist-info/AUTHORS.rst
Zeppi_ConvertX-0.1.8.dist-info/METADATA
Zeppi_ConvertX-0.1.8.dist-info/WHEEL
Zeppi_ConvertX-0.1.8.dist-info/entry_points.txt
Zeppi_ConvertX-0.1.8.dist-info/top_level.txt
Zeppi_ConvertX-0.1.8.dist-info/RECORD
