Metadata-Version: 2.1
Name: Zeppi-ConvertX
Version: 0.1.8
Summary: Convert your zeppelin notebooks to python
Home-page: https://github.com/mecsys/Zeppi_ConvertX
Author: Harsha Karpurapu
Author-email: kbsriharsha@gmail.com
License: MIT
Keywords: zeppelin convert to python notebooks interpreter
Platform: UNKNOWN
Classifier: Development Status :: 2 - Pre-Alpha
Classifier: Intended Audience :: Developers
Classifier: License :: OSI Approved :: MIT License
Classifier: Natural Language :: English
Classifier: Programming Language :: Python :: 3
Classifier: Programming Language :: Python :: 3.3
Classifier: Programming Language :: Python :: 3.4
Classifier: Programming Language :: Python :: 3.5
Classifier: Programming Language :: Python :: 3.6
